{
 "cards": [
  {
   "card": "Total Employees"
  },
  {
   "card": "New Hires (This Year)"
  },
  {
   "card": "Employee Exits (This Year)"
  }
 ],
 "charts": [
  {
   "chart": "Employees by Age",
   "width": "Full"
  },
  {
   "chart": "Gender Diversity Ratio",
   "width": "Full"
  },
  {
   "chart": "MIS - Vajra Manpower: Cost_center vs Accounts_officer",
   "width": "Full"
  },
  {
   "chart": "Employees by Type",
   "width": "Full"
  },
  {
   "chart": "Employees by Branch",
   "width": "Full"
  },
  {
   "chart": "Designation Wise Employee Count",
   "width": "Full"
  },
  {
   "chart": "Department Wise Employee Count",
   "width": "Full"
  },
  {
   "chart": "Attendance Count",
   "width": "Full"
  },
  {
   "chart": "Employee Leave Balance",
   "width": "Full"
  }
 ],
 "creation": "2022-08-24 17:57:50.156258",
 "dashboard_name": "Human Resource",
 "docstatus": 0,
 "doctype": "Dashboard",
 "idx": 0,
 "is_default": 0,
 "is_standard": 1,
 "modified": "2024-07-19 14:42:35.465148",
 "modified_by": "Administrator",
 "module": "HR",
 "name": "Human Resource",
 "owner": "birendra.bhuejel@thimphutechpark.bt"
}